MANIFEST.in
setup.py
thugperf/__init__.py
thugperf/runner.py
thugperf.egg-info/PKG-INFO
thugperf.egg-info/SOURCES.txt
thugperf.egg-info/dependency_links.txt
thugperf.egg-info/entry_points.txt
thugperf.egg-info/requires.txt
thugperf.egg-info/top_level.txt
thugperf/vendor/Darwin/chromedriver
thugperf/vendor/Linux/chromedriver