Metadata-Version: 1.1
Name: thugperf
Version: 0.0.4
Summary: simple page load time measurement tool
Home-page: https://github.com/guilhermef/thugperf
Author: Guilherme Souza
Author-email: guivideojob@gmail.com
License: MIT
Keywords: web load time measurement tool
Platform: UNKNOWN
Classifier: Development Status :: 4 - Beta
Classifier: Intended Audience :: Developers
Classifier: License :: OSI Approved :: MIT License
Classifier: Natural Language :: English
Classifier: Operating System :: MacOS
Classifier: Operating System :: POSIX :: Linux
Classifier: Programming Language :: Python :: 2.7
